ospgrillage/__init__.py
ospgrillage/load.py
ospgrillage/material.py
ospgrillage/members.py
ospgrillage/mesh.py
ospgrillage/osp_grillage.py
ospgrillage/postprocessing.py
ospgrillage/static.py
ospgrillage-0.3.1.dist-info/LICENSE.md
ospgrillage-0.3.1.dist-info/METADATA
ospgrillage-0.3.1.dist-info/WHEEL
ospgrillage-0.3.1.dist-info/top_level.txt
ospgrillage-0.3.1.dist-info/RECORD
