Metadata-Version: 2.1
Name: ospgrillage
Version: 0.3.1
Summary: Bridge deck grillage analysis using OpenSeesPy
Author-email: Monash Smart Structures <colin.caprani@monash.edu>, Jun Wei Ngan <jun.ngan@monash.edu>, Colin <colin.caprani@monash.edu>
License: MIT
Project-URL: Homepage, https://monashsmartstructures.github.io/ospgrillage/
Project-URL: Documentation, https://monashsmartstructures.github.io/ospgrillage/
Project-URL: Source, https://github.com/MonashSmartStructures/ospgrillage
Project-URL: Tracker, https://github.com/MonashSmartStructures/ospgrillage/issues
Keywords: bridge, grillage, openseespy
Platform: any
Classifier: Development Status :: 4 - Beta
Classifier: Topic :: Scientific/Engineering
Classifier: Environment :: Console
Classifier: Intended Audience :: Science/Research
Classifier: Programming Language :: Python :: 3 :: Only
Classifier: License :: OSI Approved :: MIT License
Classifier: Natural Language :: English
Classifier: Operating System :: POSIX :: Linux
Classifier: Operating System :: MacOS :: MacOS X
Classifier: Operating System :: Microsoft :: Windows
Classifier: Programming Language :: Python :: 3.8
Classifier: Programming Language :: Python :: 3.9
Classifier: Programming Language :: Python :: 3.10
Classifier: Programming Language :: Python :: 3.11
Requires-Python: >=3.8
License-File: LICENSE.md
Requires-Dist: openseespy >=3.2.2.6
Requires-Dist: opsvis ~=0.95.5
Requires-Dist: openseespyvis >=0.0.6
Requires-Dist: matplotlib
Requires-Dist: numpy
Requires-Dist: pandas
Requires-Dist: scipy
Requires-Dist: xarray
Provides-Extra: test
Requires-Dist: pytest >=6.2.2 ; extra == 'test'
